lr_model/VERSION
lr_model/__init__.py
lr_model/config.yml
lr_model/predict.py
lr_model/run_validation.py
lr_model/train.py
lr_model/config/__init__.py
lr_model/config/core.py
lr_model/processing/__init__.py
lr_model/processing/dataprocessing.py
lr_model/trained_models/LR_models.sav
lr_model/trained_models/__init__.py
lr_model/trained_models/feature_s1.pkl
lr_model/trained_models/feature_s2.pkl
NLI_lr_model-0.0.2.dist-info/METADATA
NLI_lr_model-0.0.2.dist-info/WHEEL
NLI_lr_model-0.0.2.dist-info/top_level.txt
NLI_lr_model-0.0.2.dist-info/RECORD
